ecghelper/__init__.py
ecghelper/__main__.py
ecghelper/convert.py
ecghelper/record.py
ecghelper/utils.py
ecghelper/waveform.py
ecghelper-0.8.3.dist-info/METADATA
ecghelper-0.8.3.dist-info/WHEEL
ecghelper-0.8.3.dist-info/RECORD
