Metadata-Version: 2.3
Name: ecghelper
Version: 0.8.3
Summary: Tools to load and process electrocardiogram data.
Classifier: Operating System :: OS Independent
Classifier: Programming Language :: Python :: 3
Requires-Python: >=3.11
Requires-Dist: dandelion-data-schema>=1.3.0
Requires-Dist: joblib>=1.5.0
Requires-Dist: lxml>=4.9.2
Requires-Dist: numpy>=2.0.0
Requires-Dist: pyedflib==0.1.42
Requires-Dist: tqdm>=4.65.0
Requires-Dist: types-lxml>=2023.3.28
Requires-Dist: wfdb>=4.3.0
Provides-Extra: dev
Requires-Dist: build; extra == 'dev'
Requires-Dist: pip; extra == 'dev'
Requires-Dist: pytest; extra == 'dev'
Requires-Dist: twine; extra == 'dev'
